cryptob/__init__.py
cryptob/__main__.py
cryptob-1.6.0.dist-info/licenses/LICENSE
cryptob-1.6.0.dist-info/METADATA
cryptob-1.6.0.dist-info/WHEEL
cryptob-1.6.0.dist-info/entry_points.txt
cryptob-1.6.0.dist-info/top_level.txt
cryptob-1.6.0.dist-info/RECORD
